CHANGES.txt
LICENSE.txt
MANIFEST.in
README.txt
buildout.cfg
setup.py
src/j01/__init__.py
src/j01.editor.egg-info/PKG-INFO
src/j01.editor.egg-info/SOURCES.txt
src/j01.editor.egg-info/dependency_links.txt
src/j01.editor.egg-info/namespace_packages.txt
src/j01.editor.egg-info/not-zip-safe
src/j01.editor.egg-info/requires.txt
src/j01.editor.egg-info/top_level.txt
src/j01/editor/__init__.py
src/j01/editor/configure.zcml
src/j01/editor/interfaces.py
src/j01/editor/util.py
src/j01/editor/widget.py
src/j01/editor/widget.zcml
src/j01/editor/cdn/configure.zcml
src/j01/editor/cdn/css.zcml
src/j01/editor/cdn/js.zcml
src/j01/editor/cdn/min.zcml
src/j01/editor/cdn/css/quill.bubble.css
src/j01/editor/cdn/css/quill.core.css
src/j01/editor/cdn/css/quill.snow.css
src/j01/editor/cdn/js/QuillDeltaToHtmlConverter.bundle.js
src/j01/editor/cdn/js/quill.core.js
src/j01/editor/cdn/js/quill.js
src/j01/editor/cdn/min/quill.min.js
src/j01/editor/cdn/min/quill.min.js.map
src/j01/editor/tests/__init__.py
src/j01/editor/tests/checker.txt
src/j01/editor/tests/tests.py
src/j01/editor/tests/util.txt